simple_menus/__init__.py
simple_menus/admin.py
simple_menus/apps.py
simple_menus/models.py
simple_menus/version.py
simple_menus/migrations/0001_initial.py
simple_menus/migrations/0002_menu_template_string.py
simple_menus/migrations/__init__.py
simple_menus/templates/menu.html
simple_menus/templatetags/__init__.py
simple_menus/templatetags/simplemenus_tags.py
simple_menus/wagtail/__init__.py
simple_menus/wagtail/admin.py
django_simple_menus-0.0.1.dist-info/LICENSE
django_simple_menus-0.0.1.dist-info/METADATA
django_simple_menus-0.0.1.dist-info/WHEEL
django_simple_menus-0.0.1.dist-info/top_level.txt
django_simple_menus-0.0.1.dist-info/RECORD
